torchprobe/__init__.py
torchprobe-0.0.1.dist-info/WHEEL
torchprobe-0.0.1.dist-info/METADATA
torchprobe-0.0.1.dist-info/RECORD
