Metadata-Version: 2.3
Name: torchprobe
Version: 0.0.1
Summary: A PyTorch toolkit for model profiling and runtime inspection.
Author: KurisuNya
Author-email: KurisuNya <cuizhu1216@gmail.com>
Requires-Python: >=3.9
